effmap/__init__.py
effmap/hst.py
effmap/regressor.py
effmap-0.0.15.dist-info/LICENSE.txt
effmap-0.0.15.dist-info/METADATA
effmap-0.0.15.dist-info/WHEEL
effmap-0.0.15.dist-info/top_level.txt
effmap-0.0.15.dist-info/RECORD
