Metadata-Version: 2.1
Name: effmap
Version: 0.0.15
Summary: Custom regressor and HST object
Home-page: https://github.com/ivanokhotnikov/effmap/tree/master
Author: Ivan Okhotnikov
Author-email: ivan.okhotnikov@outlook.com
License: UNKNOWN
Platform: UNKNOWN
Classifier: Programming Language :: Python :: 3
Classifier: License :: OSI Approved :: MIT License
Classifier: Operating System :: OS Independent
Requires-Python: >=3.6
